etripy/__init__.py
etripy/error.py
etripy/http.py
etripy/client/__init__.py
etripy/client/language.py
etripy/client/visual.py
etripy/client/voice.py
etripy/model/__init__.py
etripy/model/etc.py
etripy/model/language/__init__.py
etripy/model/language/analysis.py
etripy/model/language/base.py
etripy/model/language/etc.py
etripy/model/language/etcqa.py
etripy/model/language/wiseqa.py
etripy/model/visual/__init__.py
etripy/model/visual/image.py
etripy/model/visual/video.py
etripy/model/voice/__init__.py
etripy/sync/__init__.py
etripy/sync/http.py
etripy/sync/language.py
etripy/sync/visual.py
etripy/sync/voice.py
tests/__init__.py
tests/async/__init__.py
tests/async/language/__init__.py
tests/async/language/conftest.py
tests/async/language/test_QA.py
tests/async/language/test_analysis.py
tests/async/visual/__init__.py
tests/async/visual/conftest.py
tests/async/visual/test_image.py
tests/async/visual/test_video.py
tests/async/voice/__init__.py
tests/async/voice/conftest.py
tests/async/voice/test_voice.py
tests/sync/__init__.py
tests/sync/language/__init__.py
tests/sync/language/conftest.py
tests/sync/language/test_QA.py
tests/sync/language/test_analysis.py
tests/sync/visual/__init__.py
tests/sync/visual/conftest.py
tests/sync/visual/test_image.py
tests/sync/visual/test_video.py
tests/sync/voice/__init__.py
tests/sync/voice/conftest.py
tests/sync/voice/test_voice.py
etripy-1.3.1.dist-info/LICENSE
etripy-1.3.1.dist-info/METADATA
etripy-1.3.1.dist-info/WHEEL
etripy-1.3.1.dist-info/top_level.txt
etripy-1.3.1.dist-info/RECORD
