Metadata-Version: 2.1
Name: etripy
Version: 1.3.1
Summary: 인공지능 기술을 체험할 수 있는 공공 인공지능 오픈 API Wrapper
Home-page: https://github.com/VoidAsMad/ETRI
Author: VoidAsMad
Author-email: star@devksy.xyz
License: MIT
Requires-Python: >=3.6
License-File: LICENSE
Requires-Dist: requests
Requires-Dist: aiohttp
Requires-Dist: pydub
